fastcbv/__init__.py
fastcbv/decorators.py
fastcbv/routing.py
fastcbv/views.py
fastcbv-0.1.0.dist-info/METADATA
fastcbv-0.1.0.dist-info/WHEEL
fastcbv-0.1.0.dist-info/licenses/LICENSE
fastcbv-0.1.0.dist-info/RECORD
