Metadata-Version: 2.4
Name: fastcbv
Version: 0.1.0
Summary: Class-based views for FastAPI
Project-URL: Homepage, https://github.com/tcdent/fastapi-cbv
Project-URL: Repository, https://github.com/tcdent/fastapi-cbv
Author-email: Travis Dent <root@a10k.co>
License: MIT
License-File: LICENSE
Keywords: api,cbv,class-based-views,fastapi
Classifier: Development Status :: 4 - Beta
Classifier: Framework :: FastAPI
Classifier: Intended Audience :: Developers
Classifier: License :: OSI Approved :: MIT License
Classifier: Programming Language :: Python :: 3.12
Classifier: Programming Language :: Python :: 3.13
Requires-Python: >=3.12
Requires-Dist: fastapi>=0.115.0
